lol_id_tools/__init__.py
lol_id_tools/functions.py
lol_id_tools/get_simple_id.py
lol_id_tools/logger.py
lol_id_tools/parsing/__init__.py
lol_id_tools/parsing/data_parser.py
lol_id_tools/parsing/local_data/locales.json
lol_id_tools/parsing/local_data/nicknames.json
lol_id_tools/parsing/local_data_parser.py
lol_id_tools/parsing/lol_object_data.py
lol_id_tools/parsing/parse_ddragon.py
lol_id_tools-2.0.0.dist-info/LICENSE
lol_id_tools-2.0.0.dist-info/WHEEL
lol_id_tools-2.0.0.dist-info/METADATA
lol_id_tools-2.0.0.dist-info/RECORD
